fallbacks/__init__.py
fallbacks/_version.py
fallbacks/core.py
fallbacks/py.typed
fallbacks/tests/__init__.py
fallbacks/tests/__main__.py
fallbacks/tests/core.py
fallbacks-0.1.0.dist-info/LICENSE
fallbacks-0.1.0.dist-info/METADATA
fallbacks-0.1.0.dist-info/WHEEL
fallbacks-0.1.0.dist-info/top_level.txt
fallbacks-0.1.0.dist-info/RECORD
